tracksim/__init__.py
tracksim/cell_models.py
tracksim/example_trips.py
tracksim/pack_models.py
tracksim/temperature_models.py
tracksim/tracksim.py
tracksim/utils.py
tracksim/vehicle_models.py
"tracksim/PyBatteryID_models/model_n,l=3,4.npy"
tracksim/battery_data/Sheikh2025_OCV.csv
tracksim/battery_data/Zheng2024_OCV.csv
tracksim/example_trip_data/Weinreich2025_E45_1.csv
tracksim/example_trip_data/Weinreich2025_E45_2.csv
tracksim/example_trip_data/udds.csv
tracksim/example_trip_data/us06.csv
pytracksim-1.3.0.dist-info/METADATA
pytracksim-1.3.0.dist-info/WHEEL
pytracksim-1.3.0.dist-info/licenses/LICENSE
pytracksim-1.3.0.dist-info/RECORD
