Metadata-Version: 2.4
Name: pytracksim
Version: 1.3.0
Summary: A multilevel battery simulation tool for realistic battery cell data
Author-email: Nicolai Weinreich <nawe@energy.aau.dk>
License-Expression: MIT
License-File: LICENSE
Classifier: Operating System :: OS Independent
Classifier: Programming Language :: Python :: 3
Requires-Python: >=3.12
Requires-Dist: libsumo>=1.20
Requires-Dist: matplotlib
Requires-Dist: numpy
Requires-Dist: pandas
Requires-Dist: scipy
Requires-Dist: tqdm
